datasette_sandstorm_support/__init__.py
datasette_sandstorm_support-0.2.dist-info/LICENSE
datasette_sandstorm_support-0.2.dist-info/METADATA
datasette_sandstorm_support-0.2.dist-info/WHEEL
datasette_sandstorm_support-0.2.dist-info/entry_points.txt
datasette_sandstorm_support-0.2.dist-info/top_level.txt
datasette_sandstorm_support-0.2.dist-info/RECORD
