Metadata-Version: 2.1
Name: datasette-sandstorm-support
Version: 0.2
Summary: Authentication and permissions for Datasette on Sandstorm
Home-page: https://github.com/simonw/datasette-sandstorm-support
Author: Simon Willison
License: Apache License, Version 2.0
Project-URL: Issues, https://github.com/simonw/datasette-sandstorm-support/issues
Project-URL: CI, https://github.com/simonw/datasette-sandstorm-support/actions
Project-URL: Changelog, https://github.com/simonw/datasette-sandstorm-support/releases
Classifier: Framework :: Datasette
Classifier: License :: OSI Approved :: Apache Software License
Requires-Python: >=3.7
License-File: LICENSE
Requires-Dist: datasette
Provides-Extra: test
Requires-Dist: pytest ; extra == 'test'
Requires-Dist: pytest-asyncio ; extra == 'test'
